LICENSE
README.md
setup.py
MukeshAPI/__init__.py
MukeshAPI/func.py
MukeshAPI/truth_dare.py
MukeshAPI/words.py
MukeshAPI.egg-info/PKG-INFO
MukeshAPI.egg-info/SOURCES.txt
MukeshAPI.egg-info/dependency_links.txt
MukeshAPI.egg-info/requires.txt
MukeshAPI.egg-info/top_level.txt